README.rst
setup.cfg
setup.py
src/mlplatformutils/__init__.py
src/mlplatformutils.egg-info/PKG-INFO
src/mlplatformutils.egg-info/SOURCES.txt
src/mlplatformutils.egg-info/dependency_links.txt
src/mlplatformutils.egg-info/requires.txt
src/mlplatformutils.egg-info/top_level.txt
src/mlplatformutils/core/__init__.py
src/mlplatformutils/core/app_insights_logger.py
src/mlplatformutils/core/freshnessutils.py
src/mlplatformutils/core/lineagegraph.py
src/mlplatformutils/core/pandascoreutils.py
src/mlplatformutils/core/pandasutils.py
src/mlplatformutils/core/platformutils.py
src/mlplatformutils/core/sparkcoreutils.py
src/mlplatformutils/core/sparkutils.py
src/mlplatformutils/core/version.py