Metadata-Version: 2.1
Name: mlplatformutils
Version: 0.9.4
Author: Keshav Singh
Author-email: keshav_singh@hotmail.com
License: MIT
Keywords: mlplatformutils
Classifier: Programming Language :: Python :: 3.8
